flowmium/__init__.py
flowmium/_flow.py
flowmium/serializers.py
flowmium-0.0.2.dist-info/METADATA
flowmium-0.0.2.dist-info/WHEEL
flowmium-0.0.2.dist-info/RECORD
